sequenticon/Sequenticon.py
sequenticon/__init__.py
sequenticon/tools.py
sequenticon/version.py
sequenticon/report_assets/logo.png
sequenticon/report_assets/report_style.css
sequenticon/report_assets/report_template.pug
sequenticon-0.1.8.dist-info/licenses/LICENSE
sequenticon-0.1.8.dist-info/METADATA
sequenticon-0.1.8.dist-info/WHEEL
sequenticon-0.1.8.dist-info/top_level.txt
sequenticon-0.1.8.dist-info/RECORD
