Metadata-Version: 2.4
Name: sequenticon
Version: 0.1.8
Summary: Generate human-friendly icons from DNA sequences
Author: Zulko
License-Expression: MIT
Project-URL: Homepage, https://github.com/Edinburgh-Genome-Foundry/sequenticon
Keywords: DNA,sequence,barcoding,sequenticon,identicon,hash
License-File: LICENSE
Requires-Dist: Biopython
Requires-Dist: pydenticon
Requires-Dist: snapgene_reader
Requires-Dist: flametree
Requires-Dist: pdf_reports
Dynamic: license-file
